{
  "DisplayName": "SaleItemReportTableVerification",
  "Tooltip": null,
  "HelpLink": null,
  "Color": null,
  "OriginalIconFileName": null,
  "Arguments": [
    {
      "Name": "str_in_URL",
      "DisplayName": "str_in_URL",
      "Category": null,
      "Tooltip": null,
      "Placeholder": null,
      "Widget": null,
      "IsRequired": false,
      "IsPrincipal": true,
      "ArgumentType": 0,
      "DataSourceItems": null
    },
    {
      "Name": "str_in_Test_ID",
      "DisplayName": "str_in_Test_ID",
      "Category": null,
      "Tooltip": null,
      "Placeholder": null,
      "Widget": null,
      "IsRequired": false,
      "IsPrincipal": true,
      "ArgumentType": 0,
      "DataSourceItems": null
    },
    {
      "Name": "int_in_Report_ID",
      "DisplayName": "int_in_Report_ID",
      "Category": null,
      "Tooltip": null,
      "Placeholder": null,
      "Widget": null,
      "IsRequired": false,
      "IsPrincipal": true,
      "ArgumentType": 0,
      "DataSourceItems": null
    },
    {
      "Name": "str_in_MerchantMID",
      "DisplayName": "str_in_MerchantMID",
      "Category": null,
      "Tooltip": null,
      "Placeholder": null,
      "Widget": null,
      "IsRequired": false,
      "IsPrincipal": true,
      "ArgumentType": 0,
      "DataSourceItems": null
    },
    {
      "Name": "str_in_FirstName",
      "DisplayName": "str_in_FirstName",
      "Category": null,
      "Tooltip": null,
      "Placeholder": null,
      "Widget": null,
      "IsRequired": false,
      "IsPrincipal": true,
      "ArgumentType": 0,
      "DataSourceItems": null
    },
    {
      "Name": "str_in_LastName",
      "DisplayName": "str_in_LastName",
      "Category": null,
      "Tooltip": null,
      "Placeholder": null,
      "Widget": null,
      "IsRequired": false,
      "IsPrincipal": true,
      "ArgumentType": 0,
      "DataSourceItems": null
    },
    {
      "Name": "str_in_Amount",
      "DisplayName": "str_in_Amount",
      "Category": null,
      "Tooltip": null,
      "Placeholder": null,
      "Widget": null,
      "IsRequired": false,
      "IsPrincipal": true,
      "ArgumentType": 0,
      "DataSourceItems": null
    },
    {
      "Name": "str_in_TransactionID",
      "DisplayName": "str_in_TransactionID",
      "Category": null,
      "Tooltip": null,
      "Placeholder": null,
      "Widget": null,
      "IsRequired": false,
      "IsPrincipal": true,
      "ArgumentType": 0,
      "DataSourceItems": null
    },
    {
      "Name": "str_in_Address",
      "DisplayName": "str_in_Address",
      "Category": null,
      "Tooltip": null,
      "Placeholder": null,
      "Widget": null,
      "IsRequired": false,
      "IsPrincipal": true,
      "ArgumentType": 0,
      "DataSourceItems": null
    },
    {
      "Name": "str_in_City",
      "DisplayName": "str_in_City",
      "Category": null,
      "Tooltip": null,
      "Placeholder": null,
      "Widget": null,
      "IsRequired": false,
      "IsPrincipal": true,
      "ArgumentType": 0,
      "DataSourceItems": null
    },
    {
      "Name": "str_in_StateCode",
      "DisplayName": "str_in_StateCode",
      "Category": null,
      "Tooltip": null,
      "Placeholder": null,
      "Widget": null,
      "IsRequired": false,
      "IsPrincipal": true,
      "ArgumentType": 0,
      "DataSourceItems": null
    },
    {
      "Name": "str_in_ZipCode",
      "DisplayName": "str_in_ZipCode",
      "Category": null,
      "Tooltip": null,
      "Placeholder": null,
      "Widget": null,
      "IsRequired": false,
      "IsPrincipal": true,
      "ArgumentType": 0,
      "DataSourceItems": null
    },
    {
      "Name": "str_in_Email",
      "DisplayName": "str_in_Email",
      "Category": null,
      "Tooltip": null,
      "Placeholder": null,
      "Widget": null,
      "IsRequired": false,
      "IsPrincipal": true,
      "ArgumentType": 0,
      "DataSourceItems": null
    },
    {
      "Name": "str_in_PaymentMehod",
      "DisplayName": "str_in_PaymentMehod",
      "Category": null,
      "Tooltip": null,
      "Placeholder": null,
      "Widget": null,
      "IsRequired": false,
      "IsPrincipal": true,
      "ArgumentType": 0,
      "DataSourceItems": null
    },
    {
      "Name": "str_in_SaleItem1",
      "DisplayName": "str_in_SaleItem1",
      "Category": null,
      "Tooltip": null,
      "Placeholder": null,
      "Widget": null,
      "IsRequired": false,
      "IsPrincipal": true,
      "ArgumentType": 0,
      "DataSourceItems": null
    },
    {
      "Name": "str_in_SaleItem1ItemPice",
      "DisplayName": "str_in_SaleItem1ItemPice",
      "Category": null,
      "Tooltip": null,
      "Placeholder": null,
      "Widget": null,
      "IsRequired": false,
      "IsPrincipal": true,
      "ArgumentType": 0,
      "DataSourceItems": null
    },
    {
      "Name": "str_in_SaleItem1ItemQuantity",
      "DisplayName": "str_in_SaleItem1ItemQuantity",
      "Category": null,
      "Tooltip": null,
      "Placeholder": null,
      "Widget": null,
      "IsRequired": false,
      "IsPrincipal": true,
      "ArgumentType": 0,
      "DataSourceItems": null
    },
    {
      "Name": "str_in_SaleItem1TotalPrice",
      "DisplayName": "str_in_SaleItem1TotalPrice",
      "Category": null,
      "Tooltip": null,
      "Placeholder": null,
      "Widget": null,
      "IsRequired": false,
      "IsPrincipal": true,
      "ArgumentType": 0,
      "DataSourceItems": null
    },
    {
      "Name": "str_in_SaleItem2",
      "DisplayName": "str_in_SaleItem2",
      "Category": null,
      "Tooltip": null,
      "Placeholder": null,
      "Widget": null,
      "IsRequired": false,
      "IsPrincipal": true,
      "ArgumentType": 0,
      "DataSourceItems": null
    },
    {
      "Name": "str_in_SaleItem2ItemQuantity",
      "DisplayName": "str_in_SaleItem2ItemQuantity",
      "Category": null,
      "Tooltip": null,
      "Placeholder": null,
      "Widget": null,
      "IsRequired": false,
      "IsPrincipal": true,
      "ArgumentType": 0,
      "DataSourceItems": null
    },
    {
      "Name": "str_in_SaleItem2ItemPice",
      "DisplayName": "str_in_SaleItem2ItemPice",
      "Category": null,
      "Tooltip": null,
      "Placeholder": null,
      "Widget": null,
      "IsRequired": false,
      "IsPrincipal": true,
      "ArgumentType": 0,
      "DataSourceItems": null
    },
    {
      "Name": "str_in_SaleItem2TotalPrice",
      "DisplayName": "str_in_SaleItem2TotalPrice",
      "Category": null,
      "Tooltip": null,
      "Placeholder": null,
      "Widget": null,
      "IsRequired": false,
      "IsPrincipal": true,
      "ArgumentType": 0,
      "DataSourceItems": null
    },
    {
      "Name": "str_in_SaleItem3",
      "DisplayName": "str_in_SaleItem3",
      "Category": null,
      "Tooltip": null,
      "Placeholder": null,
      "Widget": null,
      "IsRequired": false,
      "IsPrincipal": true,
      "ArgumentType": 0,
      "DataSourceItems": null
    },
    {
      "Name": "str_in_SaleItem3ItemQuantity",
      "DisplayName": "str_in_SaleItem3ItemQuantity",
      "Category": null,
      "Tooltip": null,
      "Placeholder": null,
      "Widget": null,
      "IsRequired": false,
      "IsPrincipal": true,
      "ArgumentType": 0,
      "DataSourceItems": null
    },
    {
      "Name": "str_in_SaleItem3ItemPice",
      "DisplayName": "str_in_SaleItem3ItemPice",
      "Category": null,
      "Tooltip": null,
      "Placeholder": null,
      "Widget": null,
      "IsRequired": false,
      "IsPrincipal": true,
      "ArgumentType": 0,
      "DataSourceItems": null
    },
    {
      "Name": "str_in_SaleItem3TotalPrice",
      "DisplayName": "str_in_SaleItem3TotalPrice",
      "Category": null,
      "Tooltip": null,
      "Placeholder": null,
      "Widget": null,
      "IsRequired": false,
      "IsPrincipal": true,
      "ArgumentType": 0,
      "DataSourceItems": null
    }
  ]
}